{
    "version": "0.8",
    "description": "(Scoop bucket by arch3rpro) ligolo-ng - 简单方便的TUN接口的隧道 An advanced, yet simple, tunneling/pivoting tool that uses a TUN interface.",
    "homepage": "https://github.com/nicocha30/ligolo-ng",
    "license": "GPL-3.0-or-later",
    "architecture": {
        "64bit": {
            "url": [
                "https://github.com/nicocha30/ligolo-ng/releases/download/v0.8/ligolo-ng_agent_0.8_windows_amd64.zip",
                "https://github.com/nicocha30/ligolo-ng/releases/download/v0.8/ligolo-ng_proxy_0.8_windows_amd64.zip"
            ],
            "hash": [
                "898ce05bc7b4190a151aa9e2d2ae64b355341330b235430bffa28732cd68361a",
                "d55b0072f0e91c732fa4610d64cc5136767718cd640eb255037597bc01742a76"
            ]
        },
        "arm64": {
            "url": [
                "https://github.com/nicocha30/ligolo-ng/releases/download/v0.8/ligolo-ng_agent_0.8_windows_arm64.zip",
                "https://github.com/nicocha30/ligolo-ng/releases/download/v0.8/ligolo-ng_proxy_0.8_windows_arm64.zip"
            ],
            "hash": [
                "fc26c2f675f5ed336ec4f3b66f4693add05d9144eab2522753f11d557108d179",
                "6464cfa97f162cd6a4c4cf3d4b6ccf7e425772717bdd4bf0483fa94a78dcf774"
            ]
        }
    },
    "bin": [
        [
            "proxy.exe",
            "ligolo-ng_proxy"
        ],
        [
            "agent.exe",
            "ligolo-ng_agent"
        ]
    ],
    "checkver": "github",
    "autoupdate": {
        "architecture": {
            "64bit": {
                "url": [
                    "https://github.com/nicocha30/ligolo-ng/releases/download/v$version/ligolo-ng_agent_$version_windows_amd64.zip",
                    "https://github.com/nicocha30/ligolo-ng/releases/download/v$version/ligolo-ng_proxy_$version_windows_amd64.zip"
                ]
            },
            "arm64": {
                "url": [
                    "https://github.com/nicocha30/ligolo-ng/releases/download/v$version/ligolo-ng_agent_$version_windows_arm64.zip",
                    "https://github.com/nicocha30/ligolo-ng/releases/download/v$version/ligolo-ng_proxy_$version_windows_arm64.zip"
                ]
            }
        }
    }
}
