{
    "version": "4.2.16",
    "description": "Xterminal - 更好用的开发工具，但不止于Terminal、Note、SSH",
    "homepage": "https://www.terminal.icu/",
    "license": "Freeware",
    "architecture": {
        "64bit": {
            "url": "https://cdn-cn.xterminal.cn/xterminal/XTerminal-4.2.16-win-x64-installer.exe#/dl.7z",
            "hash": "e7b1ae372ff39c0782e368e3577dbaee79ade6a58b492d1865797d917ef1388c",
            "pre_install": [
                "Expand-7zipArchive \"$dir\\`$PLUGINSDIR\\app-64.7z\" \"$dir\"",
                "Remove-Item \"$dir\\`$*\", \"$dir\\Uninstall*\" -Force -Recurse"
            ]
        }
    },
    "shortcuts": [
        [
            "XTerminal.exe",
            "XTerminal"
        ]
    ],
    "checkver": {
        "url": "https://api.xterminal.cn/server/electron/version3",
        "jsonpath": "$.windows.version"
    },
    "n": "cracvi",
    "autoupdate": {
        "architecture": {
            "64bit": {
                "url": "https://cdn-cn.xterminal.cn/xterminal/XTerminal-$version-win-x64-installer.exe#/dl.7z"
            }
        }
    }
}
